{
    "NAME": "Kuwat, le Dissident",
    "TYPE": "CHARACTER",
    "SUB_TYPE": [
        "Mage"
    ],
    "ATTRIBUTES": {
        "MOUTAIN": "5",
        "FOREST": "5",
        "OCEAN": "5",
        "HAND_COST": "4",
        "RESERVE_COST": "4"
    },
    "EFECTS": "{J} Vous pouvez sacrifier un Personnage dans mon Expédition. Si vous le faites, je perds [FLEETING_CHAR].",
    "ILLUSTRATOR": "",
    "LORE": "« Il y a des portes que l'on ne doit pas ouvrir, des sceaux que l'on ne doit pas briser. Et pourtant, je le ferai. »",
    "FACTION": "Ordis",
    "RARITY": "Rare",
    "CARD_TYPE": "Booster",
    "SET": "Core set - Au-delà des portes",
    "IMAGE": "https://altered-prod-eu.s3.amazonaws.com/Art/CORE/CARDS/ALT_CORE_B_YZ_15/JPG/fr_FR/5da2f66a0b16dbf584fa9608c370ab62.jpg",
    "NUMBER": 15
}