{
    "NAME": "Moonlight Jellyfish",
    "TYPE": "CHARACTER",
    "SUB_TYPE": [
        "Spirit"
    ],
    "ATTRIBUTES": {
        "MOUTAIN": "0",
        "FOREST": "1",
        "OCEAN": "1",
        "HAND_COST": "1",
        "RESERVE_COST": "1"
    },
    "EFECTS": "When I'm sacrificed, if I'm not [[Fleeting]] — Put me in Reserve.",
    "ILLUSTRATOR": "",
    "LORE": "Theoretically, transdifferentiation can go on indefinitely, effectively rendering the jellyfish biologically immortal... and squishy.",
    "FACTION": "Yzmir",
    "RARITY": "Common",
    "CARD_TYPE": "Booster",
    "SET": "Core set - Beyond the Gates",
    "IMAGE": "https://altered-prod-eu.s3.amazonaws.com/Art/CORE/CARDS/ALT_CORE_B_YZ_05/JPG/en_US/7780e503f0b1a5a4a493ddb2371a16ab.jpg",
    "NUMBER": 5
}