{
    "NAME": "Hathor",
    "TYPE": "CHARACTER",
    "SUB_TYPE": [
        "Artiste",
        "Divinité"
    ],
    "ATTRIBUTES": {
        "MOUTAIN": "3",
        "FOREST": "3",
        "OCEAN": "0",
        "HAND_COST": "2",
        "RESERVE_COST": "3"
    },
    "EFECTS": "{D} : Renvoyez une autre carte de votre Réserve dans votre main. (Défaussez-moi de la Réserve pour ça.)",
    "ILLUSTRATOR": "",
    "LORE": "La danse est le langage de l'âme.",
    "FACTION": "Lyra",
    "RARITY": "Commun",
    "CARD_TYPE": "Booster",
    "SET": "Core set - Au-delà des portes",
    "IMAGE": "https://altered-prod-eu.s3.amazonaws.com/Art/CORE/CARDS/ALT_CORE_B_LY_07/JPG/fr_FR/43da21cbd51fadb94b0197ec3d2db00b.jpg",
    "NUMBER": 7
}