{
    "NAME": "Hathor",
    "TYPE": "CHARACTER",
    "SUB_TYPE": [
        "Artist",
        "Deity"
    ],
    "ATTRIBUTES": {
        "MOUTAIN": "3",
        "FOREST": "3",
        "OCEAN": "0",
        "HAND_COST": "2",
        "RESERVE_COST": "2"
    },
    "EFECTS": "{D} : Return another card from your Reserve to your hand. (Discard me from Reserve to do this.)",
    "ILLUSTRATOR": "",
    "LORE": "Dance is the language of the soul.",
    "FACTION": "Yzmir",
    "RARITY": "Rare",
    "CARD_TYPE": "Booster",
    "SET": "Core set - Beyond the Gates",
    "IMAGE": "https://altered-prod-eu.s3.amazonaws.com/Art/CORE/CARDS/ALT_CORE_B_LY_07/JPG/en_US/473a28ea3ad8115f581e2e17ab743d52.jpg",
    "NUMBER": 7
}